[
  {
    "type": "FOLLOWS_PROCEDURE",
    "from": {
      "label": "Equipment",
      "key": "EQ-LF-01"
    },
    "to": {
      "label": "Procedure",
      "key": "PROC-001"
    },
    "properties": {}
  },
  {
    "type": "FOLLOWS_PROCEDURE",
    "from": {
      "label": "Equipment",
      "key": "EQ-ROT-01"
    },
    "to": {
      "label": "Procedure",
      "key": "PROC-002"
    },
    "properties": {}
  },
  {
    "type": "FOLLOWS_PROCEDURE",
    "from": {
      "label": "Equipment",
      "key": "EQ-CNV-01"
    },
    "to": {
      "label": "Procedure",
      "key": "PROC-003"
    },
    "properties": {}
  },
  {
    "type": "FOLLOWS_PROCEDURE",
    "from": {
      "label": "Equipment",
      "key": "EQ-LF-01"
    },
    "to": {
      "label": "Procedure",
      "key": "PROC-004"
    },
    "properties": {}
  },
  {
    "type": "FOLLOWS_PROCEDURE",
    "from": {
      "label": "Equipment",
      "key": "EQ-EAF-01"
    },
    "to": {
      "label": "Procedure",
      "key": "PROC-005"
    },
    "properties": {}
  },
  {
    "type": "FOLLOWS_PROCEDURE",
    "from": {
      "label": "Equipment",
      "key": "EQ-ROT-01"
    },
    "to": {
      "label": "Procedure",
      "key": "PROC-006"
    },
    "properties": {}
  },
  {
    "type": "FOLLOWS_PROCEDURE",
    "from": {
      "label": "Equipment",
      "key": "EQ-RHF-02"
    },
    "to": {
      "label": "Procedure",
      "key": "PROC-007"
    },
    "properties": {}
  },
  {
    "type": "FOLLOWS_PROCEDURE",
    "from": {
      "label": "Equipment",
      "key": "EQ-HBS-02"
    },
    "to": {
      "label": "Procedure",
      "key": "PROC-008"
    },
    "properties": {}
  },
  {
    "type": "FOLLOWS_PROCEDURE",
    "from": {
      "label": "Equipment",
      "key": "EQ-CCM-01"
    },
    "to": {
      "label": "Procedure",
      "key": "PROC-009"
    },
    "properties": {}
  },
  {
    "type": "FOLLOWS_PROCEDURE",
    "from": {
      "label": "Equipment",
      "key": "EQ-EAF-02"
    },
    "to": {
      "label": "Procedure",
      "key": "PROC-010"
    },
    "properties": {}
  },
  {
    "type": "FOLLOWS_PROCEDURE",
    "from": {
      "label": "Equipment",
      "key": "EQ-LF-01"
    },
    "to": {
      "label": "Procedure",
      "key": "PROC-011"
    },
    "properties": {}
  },
  {
    "type": "FOLLOWS_PROCEDURE",
    "from": {
      "label": "Equipment",
      "key": "EQ-CCM-01"
    },
    "to": {
      "label": "Procedure",
      "key": "PROC-012"
    },
    "properties": {}
  },
  {
    "type": "FOLLOWS_PROCEDURE",
    "from": {
      "label": "Equipment",
      "key": "EQ-HBS-01"
    },
    "to": {
      "label": "Procedure",
      "key": "PROC-013"
    },
    "properties": {}
  },
  {
    "type": "FOLLOWS_PROCEDURE",
    "from": {
      "label": "Equipment",
      "key": "EQ-CR-03"
    },
    "to": {
      "label": "Procedure",
      "key": "PROC-014"
    },
    "properties": {}
  },
  {
    "type": "FOLLOWS_PROCEDURE",
    "from": {
      "label": "Equipment",
      "key": "EQ-ROT-01"
    },
    "to": {
      "label": "Procedure",
      "key": "PROC-015"
    },
    "properties": {}
  },
  {
    "type": "FOLLOWS_PROCEDURE",
    "from": {
      "label": "Equipment",
      "key": "EQ-BF-01"
    },
    "to": {
      "label": "Procedure",
      "key": "PROC-016"
    },
    "properties": {}
  },
  {
    "type": "FOLLOWS_PROCEDURE",
    "from": {
      "label": "Equipment",
      "key": "EQ-RMS-01"
    },
    "to": {
      "label": "Procedure",
      "key": "PROC-017"
    },
    "properties": {}
  },
  {
    "type": "FOLLOWS_PROCEDURE",
    "from": {
      "label": "Equipment",
      "key": "EQ-HBS-02"
    },
    "to": {
      "label": "Procedure",
      "key": "PROC-018"
    },
    "properties": {}
  },
  {
    "type": "FOLLOWS_PROCEDURE",
    "from": {
      "label": "Equipment",
      "key": "EQ-CR-03"
    },
    "to": {
      "label": "Procedure",
      "key": "PROC-019"
    },
    "properties": {}
  },
  {
    "type": "FOLLOWS_PROCEDURE",
    "from": {
      "label": "Equipment",
      "key": "EQ-FMS-01"
    },
    "to": {
      "label": "Procedure",
      "key": "PROC-020"
    },
    "properties": {}
  },
  {
    "type": "FOLLOWS_PROCEDURE",
    "from": {
      "label": "Equipment",
      "key": "EQ-LF-02"
    },
    "to": {
      "label": "Procedure",
      "key": "PROC-021"
    },
    "properties": {}
  },
  {
    "type": "FOLLOWS_PROCEDURE",
    "from": {
      "label": "Equipment",
      "key": "EQ-RHF-01"
    },
    "to": {
      "label": "Procedure",
      "key": "PROC-022"
    },
    "properties": {}
  },
  {
    "type": "FOLLOWS_PROCEDURE",
    "from": {
      "label": "Equipment",
      "key": "EQ-RHF-01"
    },
    "to": {
      "label": "Procedure",
      "key": "PROC-023"
    },
    "properties": {}
  },
  {
    "type": "FOLLOWS_PROCEDURE",
    "from": {
      "label": "Equipment",
      "key": "EQ-RMS-02"
    },
    "to": {
      "label": "Procedure",
      "key": "PROC-024"
    },
    "properties": {}
  },
  {
    "type": "FOLLOWS_PROCEDURE",
    "from": {
      "label": "Technician",
      "key": "T1004"
    },
    "to": {
      "label": "Procedure",
      "key": "PROC-001"
    },
    "properties": {}
  },
  {
    "type": "FOLLOWS_PROCEDURE",
    "from": {
      "label": "Technician",
      "key": "T1013"
    },
    "to": {
      "label": "Procedure",
      "key": "PROC-001"
    },
    "properties": {}
  },
  {
    "type": "FOLLOWS_PROCEDURE",
    "from": {
      "label": "Technician",
      "key": "T1002"
    },
    "to": {
      "label": "Procedure",
      "key": "PROC-002"
    },
    "properties": {}
  },
  {
    "type": "FOLLOWS_PROCEDURE",
    "from": {
      "label": "Technician",
      "key": "T1016"
    },
    "to": {
      "label": "Procedure",
      "key": "PROC-002"
    },
    "properties": {}
  },
  {
    "type": "FOLLOWS_PROCEDURE",
    "from": {
      "label": "Technician",
      "key": "T1011"
    },
    "to": {
      "label": "Procedure",
      "key": "PROC-003"
    },
    "properties": {}
  },
  {
    "type": "FOLLOWS_PROCEDURE",
    "from": {
      "label": "Technician",
      "key": "T1010"
    },
    "to": {
      "label": "Procedure",
      "key": "PROC-003"
    },
    "properties": {}
  },
  {
    "type": "FOLLOWS_PROCEDURE",
    "from": {
      "label": "Technician",
      "key": "T1023"
    },
    "to": {
      "label": "Procedure",
      "key": "PROC-004"
    },
    "properties": {}
  },
  {
    "type": "FOLLOWS_PROCEDURE",
    "from": {
      "label": "Technician",
      "key": "T1009"
    },
    "to": {
      "label": "Procedure",
      "key": "PROC-004"
    },
    "properties": {}
  },
  {
    "type": "FOLLOWS_PROCEDURE",
    "from": {
      "label": "Technician",
      "key": "T1006"
    },
    "to": {
      "label": "Procedure",
      "key": "PROC-005"
    },
    "properties": {}
  },
  {
    "type": "FOLLOWS_PROCEDURE",
    "from": {
      "label": "Technician",
      "key": "T1007"
    },
    "to": {
      "label": "Procedure",
      "key": "PROC-006"
    },
    "properties": {}
  },
  {
    "type": "FOLLOWS_PROCEDURE",
    "from": {
      "label": "Technician",
      "key": "T1016"
    },
    "to": {
      "label": "Procedure",
      "key": "PROC-006"
    },
    "properties": {}
  },
  {
    "type": "FOLLOWS_PROCEDURE",
    "from": {
      "label": "Technician",
      "key": "T1012"
    },
    "to": {
      "label": "Procedure",
      "key": "PROC-007"
    },
    "properties": {}
  },
  {
    "type": "FOLLOWS_PROCEDURE",
    "from": {
      "label": "Technician",
      "key": "T1023"
    },
    "to": {
      "label": "Procedure",
      "key": "PROC-008"
    },
    "properties": {}
  },
  {
    "type": "FOLLOWS_PROCEDURE",
    "from": {
      "label": "Technician",
      "key": "T1008"
    },
    "to": {
      "label": "Procedure",
      "key": "PROC-008"
    },
    "properties": {}
  },
  {
    "type": "FOLLOWS_PROCEDURE",
    "from": {
      "label": "Technician",
      "key": "T1017"
    },
    "to": {
      "label": "Procedure",
      "key": "PROC-008"
    },
    "properties": {}
  },
  {
    "type": "FOLLOWS_PROCEDURE",
    "from": {
      "label": "Technician",
      "key": "T1024"
    },
    "to": {
      "label": "Procedure",
      "key": "PROC-009"
    },
    "properties": {}
  },
  {
    "type": "FOLLOWS_PROCEDURE",
    "from": {
      "label": "Technician",
      "key": "T1014"
    },
    "to": {
      "label": "Procedure",
      "key": "PROC-010"
    },
    "properties": {}
  },
  {
    "type": "FOLLOWS_PROCEDURE",
    "from": {
      "label": "Technician",
      "key": "T1005"
    },
    "to": {
      "label": "Procedure",
      "key": "PROC-010"
    },
    "properties": {}
  },
  {
    "type": "FOLLOWS_PROCEDURE",
    "from": {
      "label": "Technician",
      "key": "T1019"
    },
    "to": {
      "label": "Procedure",
      "key": "PROC-011"
    },
    "properties": {}
  },
  {
    "type": "FOLLOWS_PROCEDURE",
    "from": {
      "label": "Technician",
      "key": "T1009"
    },
    "to": {
      "label": "Procedure",
      "key": "PROC-011"
    },
    "properties": {}
  },
  {
    "type": "FOLLOWS_PROCEDURE",
    "from": {
      "label": "Technician",
      "key": "T1018"
    },
    "to": {
      "label": "Procedure",
      "key": "PROC-012"
    },
    "properties": {}
  },
  {
    "type": "FOLLOWS_PROCEDURE",
    "from": {
      "label": "Technician",
      "key": "T1010"
    },
    "to": {
      "label": "Procedure",
      "key": "PROC-012"
    },
    "properties": {}
  },
  {
    "type": "FOLLOWS_PROCEDURE",
    "from": {
      "label": "Technician",
      "key": "T1023"
    },
    "to": {
      "label": "Procedure",
      "key": "PROC-012"
    },
    "properties": {}
  },
  {
    "type": "FOLLOWS_PROCEDURE",
    "from": {
      "label": "Technician",
      "key": "T1013"
    },
    "to": {
      "label": "Procedure",
      "key": "PROC-013"
    },
    "properties": {}
  },
  {
    "type": "FOLLOWS_PROCEDURE",
    "from": {
      "label": "Technician",
      "key": "T1012"
    },
    "to": {
      "label": "Procedure",
      "key": "PROC-014"
    },
    "properties": {}
  },
  {
    "type": "FOLLOWS_PROCEDURE",
    "from": {
      "label": "Technician",
      "key": "T1013"
    },
    "to": {
      "label": "Procedure",
      "key": "PROC-015"
    },
    "properties": {}
  },
  {
    "type": "FOLLOWS_PROCEDURE",
    "from": {
      "label": "Technician",
      "key": "T1002"
    },
    "to": {
      "label": "Procedure",
      "key": "PROC-016"
    },
    "properties": {}
  },
  {
    "type": "FOLLOWS_PROCEDURE",
    "from": {
      "label": "Technician",
      "key": "T1013"
    },
    "to": {
      "label": "Procedure",
      "key": "PROC-016"
    },
    "properties": {}
  },
  {
    "type": "FOLLOWS_PROCEDURE",
    "from": {
      "label": "Technician",
      "key": "T1019"
    },
    "to": {
      "label": "Procedure",
      "key": "PROC-017"
    },
    "properties": {}
  },
  {
    "type": "FOLLOWS_PROCEDURE",
    "from": {
      "label": "Technician",
      "key": "T1010"
    },
    "to": {
      "label": "Procedure",
      "key": "PROC-017"
    },
    "properties": {}
  },
  {
    "type": "FOLLOWS_PROCEDURE",
    "from": {
      "label": "Technician",
      "key": "T1024"
    },
    "to": {
      "label": "Procedure",
      "key": "PROC-018"
    },
    "properties": {}
  },
  {
    "type": "FOLLOWS_PROCEDURE",
    "from": {
      "label": "Technician",
      "key": "T1011"
    },
    "to": {
      "label": "Procedure",
      "key": "PROC-018"
    },
    "properties": {}
  },
  {
    "type": "FOLLOWS_PROCEDURE",
    "from": {
      "label": "Technician",
      "key": "T1003"
    },
    "to": {
      "label": "Procedure",
      "key": "PROC-019"
    },
    "properties": {}
  },
  {
    "type": "FOLLOWS_PROCEDURE",
    "from": {
      "label": "Technician",
      "key": "T1001"
    },
    "to": {
      "label": "Procedure",
      "key": "PROC-019"
    },
    "properties": {}
  },
  {
    "type": "FOLLOWS_PROCEDURE",
    "from": {
      "label": "Technician",
      "key": "T1012"
    },
    "to": {
      "label": "Procedure",
      "key": "PROC-020"
    },
    "properties": {}
  },
  {
    "type": "FOLLOWS_PROCEDURE",
    "from": {
      "label": "Technician",
      "key": "T1012"
    },
    "to": {
      "label": "Procedure",
      "key": "PROC-021"
    },
    "properties": {}
  },
  {
    "type": "FOLLOWS_PROCEDURE",
    "from": {
      "label": "Technician",
      "key": "T1019"
    },
    "to": {
      "label": "Procedure",
      "key": "PROC-021"
    },
    "properties": {}
  },
  {
    "type": "FOLLOWS_PROCEDURE",
    "from": {
      "label": "Technician",
      "key": "T1009"
    },
    "to": {
      "label": "Procedure",
      "key": "PROC-022"
    },
    "properties": {}
  },
  {
    "type": "FOLLOWS_PROCEDURE",
    "from": {
      "label": "Technician",
      "key": "T1022"
    },
    "to": {
      "label": "Procedure",
      "key": "PROC-022"
    },
    "properties": {}
  },
  {
    "type": "FOLLOWS_PROCEDURE",
    "from": {
      "label": "Technician",
      "key": "T1021"
    },
    "to": {
      "label": "Procedure",
      "key": "PROC-023"
    },
    "properties": {}
  },
  {
    "type": "FOLLOWS_PROCEDURE",
    "from": {
      "label": "Technician",
      "key": "T1013"
    },
    "to": {
      "label": "Procedure",
      "key": "PROC-024"
    },
    "properties": {}
  },
  {
    "type": "FOLLOWS_PROCEDURE",
    "from": {
      "label": "Technician",
      "key": "T1020"
    },
    "to": {
      "label": "Procedure",
      "key": "PROC-024"
    },
    "properties": {}
  },
  {
    "type": "FOLLOWS_PROCEDURE",
    "from": {
      "label": "Equipment",
      "key": "EQ-SPF-01"
    },
    "to": {
      "label": "Procedure",
      "key": "PROC-025"
    },
    "properties": {}
  },
  {
    "type": "FOLLOWS_PROCEDURE",
    "from": {
      "label": "Equipment",
      "key": "EQ-FMS-02"
    },
    "to": {
      "label": "Procedure",
      "key": "PROC-026"
    },
    "properties": {}
  },
  {
    "type": "FOLLOWS_PROCEDURE",
    "from": {
      "label": "Equipment",
      "key": "EQ-COL-01"
    },
    "to": {
      "label": "Procedure",
      "key": "PROC-027"
    },
    "properties": {}
  },
  {
    "type": "FOLLOWS_PROCEDURE",
    "from": {
      "label": "Equipment",
      "key": "EQ-COL-02"
    },
    "to": {
      "label": "Procedure",
      "key": "PROC-028"
    },
    "properties": {}
  },
  {
    "type": "FOLLOWS_PROCEDURE",
    "from": {
      "label": "Equipment",
      "key": "EQ-CR-01"
    },
    "to": {
      "label": "Procedure",
      "key": "PROC-029"
    },
    "properties": {}
  },
  {
    "type": "FOLLOWS_PROCEDURE",
    "from": {
      "label": "Equipment",
      "key": "EQ-CR-02"
    },
    "to": {
      "label": "Procedure",
      "key": "PROC-030"
    },
    "properties": {}
  },
  {
    "type": "FOLLOWS_PROCEDURE",
    "from": {
      "label": "Equipment",
      "key": "EQ-CNV-02"
    },
    "to": {
      "label": "Procedure",
      "key": "PROC-031"
    },
    "properties": {}
  }
]